{
    "img": "http://ludumdare.com/compo/wp-content/compo2/511439/57516-shot0-1450110119.jpg",
    "title": "Superuatakku",
    "summary": "FPS donde debemos destruir una nube que expulsa gatos que crecen al recibir daño. Desarrollado con Unity en la Ludum Dare Gran Canaria 2015 / [Ludum Dare #34](http://ludumdare.com/compo/ludum-dare-34) por el equipo «404» (no se nos ocurría un nombre ;-P).",
    "background": "Superuatakku, el nombre en clave de un experimento secreto de nuestro gobierto que intentaba acabar con el hambre creando ganado que creciera rápidamente. El gato del principal científico pulsó el botón equivocado y quedó atrapado en la subsecuente explosión, creando el cráter en el que te encuentras actualmente.\n\nLas creación de Superuatakku crecerá rápidamente, consumiento al mundo en dos minutos si no es detenido. La nube se defenderá con un ejército de malvados clones gatunos que también crecerán cuando les dispares… hasta que exploten. ¡Hazte camino hasta el núcleo y destruye Superuatakku!",
    "controls": [
        {
            "key": "W, S, A, D",
            "meaning": "mover personaje"
        },
        {
            "key": "Movimiento del ratón",
            "meaning": "apuntar"
        },
        {
            "key": "Botón izquierdo del ratón",
            "meaning": "disparar"
        }
    ],
    "credits": {
        "own": [
            {
                "title": "Gráficos y sonido",
                "people": [
                    "Joaquín Yeray Martín de la Nuez",
                    "Zayyán Perera Sosa"
                ]
            },
            {
                "title": "Programación",
                "people": [
                    "Luis Antón Canalis",
                    "Moisés J. Bonilla Caraballo",
                    "Cynthia Ramos Martínez"
                ]
            }
        ]
    },
    "links": [
        {
            "text": "Página de Supessuatakku en ludumdare.com (incluye enlaces de descarga)",
            "href": "http://ludumdare.com/compo/ludum-dare-34/?action=preview&uid=57516"
        },
        {
            "text": "Repositorio de Supessuatakku en Github",
            "href": "https://github.com/Notnasiul/LDGC2015"
        }
    ]
}
